satisfaculty/__init__.py
satisfaculty/constraint_base.py
satisfaculty/constraints.py
satisfaculty/objective_base.py
satisfaculty/objectives.py
satisfaculty/scheduler.py
satisfaculty/utils.py
satisfaculty/visualize_schedule.py
satisfaculty-0.2.0.dist-info/licenses/LICENSE
satisfaculty-0.2.0.dist-info/METADATA
satisfaculty-0.2.0.dist-info/WHEEL
satisfaculty-0.2.0.dist-info/top_level.txt
satisfaculty-0.2.0.dist-info/RECORD
