Metadata-Version: 2.4
Name: satisfaculty
Version: 0.2.0
Summary: A course scheduling optimization tool using integer linear programming
Author-email: Zachary Sunberg <zachary.sunberg@colorado.edu>
License: MIT
Project-URL: Repository, https://github.com/zsunberg/satisfaculty
Keywords: scheduling,optimization,integer-programming,course-scheduling
Classifier: License :: OSI Approved :: MIT License
Requires-Python: ~=3.12
License-File: LICENSE
Requires-Dist: pandas~=2.3
Requires-Dist: numpy~=2.4
Requires-Dist: PuLP~=3.3
Requires-Dist: matplotlib~=3.10
Provides-Extra: dev
Requires-Dist: pytest; extra == "dev"
Provides-Extra: docs
Requires-Dist: sphinx; extra == "docs"
Requires-Dist: furo; extra == "docs"
Requires-Dist: myst-parser; extra == "docs"
Dynamic: license-file
